http_client_request/__init__.py
http_client_request/py.typed
http_client_request-0.0.10.dist-info/METADATA
http_client_request-0.0.10.dist-info/WHEEL
http_client_request-0.0.10.dist-info/RECORD
